pytest_live/__init__.py
pytest_live/plugin.py
pytest_live-0.6.dist-info/LICENSE
pytest_live-0.6.dist-info/METADATA
pytest_live-0.6.dist-info/WHEEL
pytest_live-0.6.dist-info/entry_points.txt
pytest_live-0.6.dist-info/top_level.txt
pytest_live-0.6.dist-info/RECORD
