Metadata-Version: 2.1
Name: pytest-live
Version: 0.6
Summary: Live results for pytest
Home-page: https://github.com/adiralashiva8/pytest-live-results
Author: Shiva Adirala
Author-email: adiralashiva8@gmail.com
License: MIT license
Keywords: pytest,py.test,live
Platform: UNKNOWN
Classifier: Framework :: Pytest
Classifier: Programming Language :: Python
Classifier: Topic :: Software Development :: Testing
Classifier: Programming Language :: Python :: 3.7
Requires-Dist: pytest
Requires-Dist: pytest-runner
